nixWrapper/__init__.py
nixWrapper/nixWrapper.py
nixwrapper-1.1.6.dist-info/licenses/LICENSE
nixwrapper-1.1.6.dist-info/METADATA
nixwrapper-1.1.6.dist-info/WHEEL
nixwrapper-1.1.6.dist-info/top_level.txt
nixwrapper-1.1.6.dist-info/RECORD
